src/__init__.py
src/base_register.py
src/constants.py
src/exceptions.py
src/logger.py
src/schema.py
src/utils.py
fastapi_register_model_router-0.0.1.dist-info/LICENSE
fastapi_register_model_router-0.0.1.dist-info/METADATA
fastapi_register_model_router-0.0.1.dist-info/WHEEL
fastapi_register_model_router-0.0.1.dist-info/top_level.txt
fastapi_register_model_router-0.0.1.dist-info/RECORD
