Metadata-Version: 2.1
Name: fastapi-register-model-router
Version: 0.0.1
Summary: 通过将fastapi的模型自动注册路由
Home-page: https://github.com/dcshoecousa
Author: stan
Author-email: stan <gd19920125@hotmail.com>
License: Apache License
Project-URL: Homepage, https://github.com/dcshoecousa
Classifier: Programming Language :: Python :: 3
Classifier: License :: OSI Approved :: MIT License
Classifier: Operating System :: OS Independent
Requires-Python: >=3.6
License-File: LICENSE
Requires-Dist: fastapi (>=0.95.1)
Requires-Dist: tortoise-orm (>=0.19.3)
